<?xml version="1.0"?>
<!DOCTYPE hibernate-mapping PUBLIC 
	"-//Hibernate/Hibernate Mapping DTD 3.0//EN"
	"http://hibernate.sourceforge.net/hibernate-mapping-3.0.dtd">

<!-- Generated Oct 20, 2010 10:22:06 AM by Hibernate Tools 3.4.0.Beta1 -->
<hibernate-mapping>

<class
    name="org.reverse.SociosRefCodesDel"
    table="SOCIOS_REF_CODES_DEL"
>

    <composite-id
		name="id"
        class="org.reverse.SociosRefCodesDelId"
    >		
	        <key-property name="idSocio" type="java.lang.Long">
<column name="ID_SOCIO" precision="10" scale="0" />
	        </key-property>
	        <key-property name="idSucursal" type="java.lang.Short">
<column name="ID_SUCURSAL" precision="4" scale="0" />
	        </key-property>
	        <key-property name="domain" type="string">
<column name="DOMAIN" length="100" />
	        </key-property>
	        <key-property name="lowValue" type="string">
<column name="LOW_VALUE" length="240" />
	        </key-property>
	        <key-property name="fechaBorrado" type="date">
<column name="FECHA_BORRADO" length="7" />
	        </key-property>
    </composite-id>	





</class>

</hibernate-mapping>